aju_pm10_hourly_prediction/__init__.py
aju_pm10_hourly_prediction/data_cleaning.py
aju_pm10_hourly_prediction/feature_engineering.py
aju_pm10_hourly_prediction/pipeline.py
aju_pm10_hourly_prediction/prediction.py
aju_pm10_hourly_prediction/visualization.py
tests/__init__.py
tests/test_pm10_prediction.py
aju_pm10_hourly_prediction-0.1.dist-info/METADATA
aju_pm10_hourly_prediction-0.1.dist-info/WHEEL
aju_pm10_hourly_prediction-0.1.dist-info/top_level.txt
aju_pm10_hourly_prediction-0.1.dist-info/RECORD
